span_explain/__init__.py
span_explain/config.py
span_explain/lime/__init__.py
span_explain/lime/bundle.js
span_explain/lime/bundle.js.map
span_explain/lime/exceptions.py
span_explain/lime/explanation.py
span_explain/lime/index_spans.py
span_explain/lime/index_string.py
span_explain/lime/js/bar_chart.js
span_explain/lime/js/explanation.js
span_explain/lime/js/main.js
span_explain/lime/js/predict_proba.js
span_explain/lime/js/predicted_value.js
span_explain/lime/lime_base.py
span_explain/lime/lime_spans.py
span_explain/lime/lime_text.py
span_explain/lime/style.css
span_explain/lime/submodular_pick.py
span_explain/lime/test_table.html
span_explain/lime/webpack.config.js
span_explain/metrics.py
span_explain/prompts/span-extraction.txt
span_explain/span_extract/__init__.py
span_explain/span_extract/exceptions.py
span_explain/span_extract/extract.py
span_explain/span_extract/models.py
span_explain/span_extract/utils.py
span_explain/utils.py
span_explain-0.1.0.dist-info/METADATA
span_explain-0.1.0.dist-info/WHEEL
span_explain-0.1.0.dist-info/RECORD
