Metadata-Version: 2.1
Name: span-explain
Version: 0.1.0
Summary: 
Author: Sebastiaan Dijkstra
Author-email: sebastiaandijkstra@gmail.com
Maintainer: Sebastiaan Dijkstra
Maintainer-email: sebastiaandijkstra@gmail.com
Requires-Python: >=3.9,<4.0
Classifier: Programming Language :: Python :: 3
Classifier: Programming Language :: Python :: 3.9
Classifier: Programming Language :: Python :: 3.10
Classifier: Programming Language :: Python :: 3.11
Classifier: Programming Language :: Python :: 3.12
Requires-Dist: langchain (==0.1.3)
Requires-Dist: langchain-community (==0.0.15)
Requires-Dist: langchain-core (==0.1.15)
Requires-Dist: langchain-openai (==0.0.2)
Requires-Dist: matplotlib (==3.8.2)
Requires-Dist: nltk (==3.8.1)
Requires-Dist: pytest
Requires-Dist: ruff (==0.1.13)
Requires-Dist: scikit-learn (==1.3.2)
Requires-Dist: scipy (==1.11.4)
Requires-Dist: thefuzz (==0.20.0)
